{
  "timestamp": "2026-05-26 14:35:41",
  "G": 512,
  "strategies": {
    "Random": {
      "strategy": "random",
      "k_bits": [
        120,
        128,
        136,
        144,
        152,
        160,
        168,
        184,
        192,
        200,
        208,
        216,
        224,
        232,
        240,
        248,
        256,
        264,
        272,
        280,
        288,
        304,
        312,
        320,
        328,
        336,
        344,
        352,
        360,
        376,
        384,
        392,
        400,
        408,
        416,
        424,
        432,
        448,
        456,
        464,
        472,
        480,
        488,
        496
      ],
      "GAR (%)": [
        99.7,
        99.4,
        98.96,
        97.17,
        96.43,
        91.22,
        88.24,
        76.04,
        72.47,
        62.05,
        55.65,
        45.68,
        38.84,
        34.38,
        30.06,
        16.52,
        14.58,
        12.65,
        9.08,
        7.29,
        6.25,
        4.17,
        3.57,
        2.08,
        1.64,
        1.19,
        0.74,
        0.6,
        0.3,
        0.15,
        0.15,
        0.0,
        0.15,
        0.0,
        0.0,
        0.0,
        0.0,
        0.0,
        0.0,
        0.0,
        0.0,
        0.0,
        0.0,
        0.0
      ],
      "inflection_k_bits": 208
    },
    "Flip-rate": {
      "strategy": "flip_rate",
      "k_bits": [
        120,
        128,
        136,
        144,
        152,
        160,
        168,
        184,
        192,
        200,
        208,
        216,
        224,
        232,
        240,
        248,
        256,
        264,
        272,
        280,
        288,
        304,
        312,
        320,
        328,
        336,
        344,
        352,
        360,
        376,
        384,
        392,
        400,
        408,
        416,
        424,
        432,
        448,
        456,
        464,
        472,
        480,
        488,
        496
      ],
      "GAR (%)": [
        99.85,
        99.85,
        99.7,
        99.4,
        97.92,
        95.98,
        94.05,
        88.24,
        83.33,
        77.98,
        69.94,
        62.95,
        55.21,
        50.6,
        42.86,
        27.53,
        22.02,
        17.41,
        13.69,
        10.27,
        9.38,
        7.29,
        5.21,
        2.98,
        2.23,
        1.49,
        0.74,
        0.74,
        0.45,
        0.3,
        0.15,
        0.15,
        0.15,
        0.0,
        0.0,
        0.0,
        0.0,
        0.0,
        0.0,
        0.0,
        0.0,
        0.0,
        0.0,
        0.0
      ],
      "inflection_k_bits": 232
    },
    "Tanh-confidence": {
      "strategy": "tanh",
      "k_bits": [
        120,
        128,
        136,
        144,
        152,
        160,
        168,
        184,
        192,
        200,
        208,
        216,
        224,
        232,
        240,
        248,
        256,
        264,
        272,
        280,
        288,
        304,
        312,
        320,
        328,
        336,
        344,
        352,
        360,
        376,
        384,
        392,
        400,
        408,
        416,
        424,
        432,
        448,
        456,
        464,
        472,
        480,
        488,
        496
      ],
      "GAR (%)": [
        99.85,
        99.7,
        99.7,
        99.4,
        99.11,
        97.17,
        95.39,
        92.26,
        90.92,
        87.35,
        85.71,
        79.76,
        77.68,
        73.51,
        68.75,
        58.78,
        51.93,
        51.79,
        47.17,
        43.3,
        39.73,
        35.57,
        29.91,
        27.98,
        25.89,
        22.77,
        20.24,
        16.96,
        16.07,
        11.9,
        10.86,
        8.48,
        6.7,
        6.1,
        5.21,
        3.57,
        2.53,
        0.6,
        0.15,
        0.15,
        0.0,
        0.0,
        0.0,
        0.0
      ],
      "inflection_k_bits": 264
    },
    "Worst-channel": {
      "strategy": "worst",
      "k_bits": [
        120,
        128,
        136,
        144,
        152,
        160,
        168,
        184,
        192,
        200,
        208,
        216,
        224,
        232,
        240,
        248,
        256,
        264,
        272,
        280,
        288,
        304,
        312,
        320,
        328,
        336,
        344,
        352,
        360,
        376,
        384,
        392,
        400,
        408,
        416,
        424,
        432,
        448,
        456,
        464,
        472,
        480,
        488,
        496
      ],
      "GAR (%)": [
        87.8,
        77.53,
        62.8,
        51.93,
        39.88,
        26.19,
        18.6,
        16.07,
        12.8,
        9.23,
        10.12,
        6.55,
        5.51,
        5.21,
        4.46,
        2.98,
        1.79,
        1.49,
        1.34,
        0.89,
        0.45,
        0.15,
        0.45,
        0.15,
        0.45,
        0.15,
        0.0,
        0.15,
        0.15,
        0.0,
        0.0,
        0.0,
        0.0,
        0.0,
        0.0,
        0.0,
        0.0,
        0.0,
        0.0,
        0.0,
        0.0,
        0.0,
        0.0,
        0.0
      ],
      "inflection_k_bits": 144
    },
    "Oracle": {
      "strategy": "oracle",
      "k_bits": [
        120,
        128,
        136,
        144,
        152,
        160,
        168,
        184,
        192,
        200,
        208,
        216,
        224,
        232,
        240,
        248,
        256,
        264,
        272,
        280,
        288,
        304,
        312,
        320,
        328,
        336,
        344,
        352,
        360,
        376,
        384,
        392,
        400,
        408,
        416,
        424,
        432,
        448,
        456,
        464,
        472,
        480,
        488,
        496
      ],
      "GAR (%)": [
        100.0,
        99.7,
        99.7,
        99.7,
        99.26,
        97.77,
        96.88,
        93.45,
        88.39,
        86.46,
        79.17,
        71.88,
        65.62,
        59.23,
        52.53,
        34.23,
        28.72,
        25.0,
        19.94,
        15.03,
        11.9,
        9.23,
        6.7,
        4.32,
        2.68,
        2.53,
        1.64,
        1.34,
        0.6,
        0.74,
        0.15,
        0.15,
        0.15,
        0.15,
        0.0,
        0.0,
        0.0,
        0.0,
        0.0,
        0.0,
        0.0,
        0.0,
        0.0,
        0.0
      ],
      "inflection_k_bits": 240
    }
  }
}